src/Helloworld.py
src/__init__.py
WHY_HelloWorld-0.1.dist-info/METADATA
WHY_HelloWorld-0.1.dist-info/WHEEL
WHY_HelloWorld-0.1.dist-info/top_level.txt
WHY_HelloWorld-0.1.dist-info/RECORD
