Metadata-Version: 2.1
Name: WHY-HelloWorld
Version: 0.1
Summary: This is an Example Package
Home-page: http://example.com/HelloWorld/
Author: Why
Author-email: UNKNOWN
License: UNKNOWN
Keywords: hello world example
Platform: UNKNOWN
